Metadata-Version: 2.1
Name: pyspectrum_lib
Version: 1.0.2
Summary: Python wrapper for Spectrum math library
Home-page: https://sdk.brainbit.com/lib-spectrum/
Author: Brainbit Inc.
Author-email: support@brainbit.com
License: MIT
Classifier: Programming Language :: Python :: 3
Classifier: License :: OSI Approved :: MIT License
Classifier: Operating System :: Microsoft :: Windows
Classifier: Operating System :: MacOS
Classifier: Intended Audience :: Developers
Requires-Python: >=3.7
